py_collections/__init__.py
py_collections/collection.py
py_collections/collection_map.py
py_collections/mixins/__init__.py
py_collections/mixins/basic_operations.py
py_collections/mixins/element_access.py
py_collections/mixins/grouping.py
py_collections/mixins/math_operations.py
py_collections/mixins/navigation.py
py_collections/mixins/removal.py
py_collections/mixins/transformation.py
py_collections/mixins/utility.py
py_collections-0.1.4.dist-info/METADATA
py_collections-0.1.4.dist-info/WHEEL
py_collections-0.1.4.dist-info/licenses/LICENSE
py_collections-0.1.4.dist-info/RECORD
