Metadata-Version: 2.4
Name: py-collections
Version: 0.1.4
Summary: A Python collections library providing enhanced collection types with additional functionality
Project-URL: Homepage, https://github.com/mato777/py-collections
Project-URL: Repository, https://github.com/mato777/py-collections
Project-URL: Documentation, https://github.com/mato777/py-collections#readme
Project-URL: Bug Tracker, https://github.com/mato777/py-collections/issues
Project-URL: Source Code, https://github.com/mato777/py-collections
Author-email: Matias Gallardo <10453322+mato777@users.noreply.github.com>
Maintainer-email: Matias Gallardo <10453322+mato777@users.noreply.github.com>
License: MIT
License-File: LICENSE
Keywords: collections,data-structures,dict,functional-programming,json,list,mixin,python,serialization,utility
Classifier: Development Status :: 4 - Beta
Classifier: Intended Audience :: Developers
Classifier: License :: OSI Approved :: MIT License
Classifier: Operating System :: OS Independent
Classifier: Programming Language :: Python :: 3
Classifier: Programming Language :: Python :: 3.13
Classifier: Topic :: Software Development :: Libraries
Classifier: Topic :: Software Development :: Libraries :: Python Modules
Classifier: Typing :: Typed
Requires-Python: >=3.13
Provides-Extra: dev
Requires-Dist: black>=24.0.0; extra == 'dev'
Requires-Dist: mypy>=1.8.0; extra == 'dev'
Requires-Dist: pydantic>=2.11.7; extra == 'dev'
Requires-Dist: pytest-cov>=4.1.0; extra == 'dev'
Requires-Dist: pytest-sugar>=1.1.1; extra == 'dev'
Requires-Dist: pytest>=8.4.1; extra == 'dev'
Requires-Dist: ruff>=0.2.0; extra == 'dev'
